MANIFEST.in
setup.py
src/twitter/__init__.py
src/twitter.pants.egg-info/PKG-INFO
src/twitter.pants.egg-info/SOURCES.txt
src/twitter.pants.egg-info/dependency_links.txt
src/twitter.pants.egg-info/entry_points.txt
src/twitter.pants.egg-info/namespace_packages.txt
src/twitter.pants.egg-info/requires.txt
src/twitter.pants.egg-info/top_level.txt
src/twitter.pants.egg-info/zip-safe
src/twitter/pants/__init__.py
src/twitter/pants/binary_util.py
src/twitter/pants/thrift_util.py
src/twitter/pants/authentication/__init__.py
src/twitter/pants/authentication/netrc_util.py
src/twitter/pants/base/__init__.py
src/twitter/pants/base/abbreviate_target_ids.py
src/twitter/pants/base/address.py
src/twitter/pants/base/build_environment.py
src/twitter/pants/base/build_file.py
src/twitter/pants/base/build_file_aliases.py
src/twitter/pants/base/build_file_context.py
src/twitter/pants/base/build_file_helpers.py
src/twitter/pants/base/build_invalidator.py
src/twitter/pants/base/build_manual.py
src/twitter/pants/base/build_root.py
src/twitter/pants/base/config.py
src/twitter/pants/base/double_dag.py
src/twitter/pants/base/generator.py
src/twitter/pants/base/hash_utils.py
src/twitter/pants/base/mustache.py
src/twitter/pants/base/parse_context.py
src/twitter/pants/base/rcfile.py
src/twitter/pants/base/revision.py
src/twitter/pants/base/run_info.py
src/twitter/pants/base/target.py
src/twitter/pants/base/timer.py
src/twitter/pants/base/worker_pool.py
src/twitter/pants/base/workunit.py
src/twitter/pants/bin/__init__.py
src/twitter/pants/bin/pants_exe.py
src/twitter/pants/cache/__init__.py
src/twitter/pants/cache/artifact.py
src/twitter/pants/cache/artifact_cache.py
src/twitter/pants/cache/cache_setup.py
src/twitter/pants/cache/combined_artifact_cache.py
src/twitter/pants/cache/local_artifact_cache.py
src/twitter/pants/cache/pinger.py
src/twitter/pants/cache/read_write_artifact_cache.py
src/twitter/pants/cache/restful_artifact_cache.py
src/twitter/pants/commands/__init__.py
src/twitter/pants/commands/build.py
src/twitter/pants/commands/command.py
src/twitter/pants/commands/goal.py
src/twitter/pants/commands/help.py
src/twitter/pants/commands/py.py
src/twitter/pants/commands/register.py
src/twitter/pants/commands/setup_py.py
src/twitter/pants/docs/conf.py
src/twitter/pants/docs/gen.py
src/twitter/pants/docs/pagerank.py
